yyskmultilearn/__init__.py
yyskmultilearn/dataset.py
yyskmultilearn/utils.py
yyskmultilearn/adapt/__init__.py
yyskmultilearn/adapt/brknn.py
yyskmultilearn/adapt/mlaram.py
yyskmultilearn/adapt/mlknn.py
yyskmultilearn/adapt/mltsvm.py
yyskmultilearn/base/__init__.py
yyskmultilearn/base/base.py
yyskmultilearn/base/mock.py
yyskmultilearn/base/problem_transformation.py
yyskmultilearn/cluster/__init__.py
yyskmultilearn/cluster/balancedkmeans.py
yyskmultilearn/cluster/base.py
yyskmultilearn/cluster/fixed.py
yyskmultilearn/cluster/graphtool.py
yyskmultilearn/cluster/helpers.py
yyskmultilearn/cluster/igraph.py
yyskmultilearn/cluster/matrix.py
yyskmultilearn/cluster/networkx.py
yyskmultilearn/cluster/random.py
yyskmultilearn/embedding/__init__.py
yyskmultilearn/embedding/_mdsw.py
yyskmultilearn/embedding/classifier.py
yyskmultilearn/embedding/clems.py
yyskmultilearn/embedding/openne.py
yyskmultilearn/embedding/skembeddings.py
yyskmultilearn/embedding/unit_tests/__init__.py
yyskmultilearn/embedding/unit_tests/test_classifier.py
yyskmultilearn/ensemble/__init__.py
yyskmultilearn/ensemble/partition.py
yyskmultilearn/ensemble/rakeld.py
yyskmultilearn/ensemble/rakelo.py
yyskmultilearn/ensemble/voting.py
yyskmultilearn/ext/__init__.py
yyskmultilearn/ext/keras.py
yyskmultilearn/ext/meka.py
yyskmultilearn/model_selection/__init__.py
yyskmultilearn/model_selection/iterative_stratification.py
yyskmultilearn/model_selection/measures.py
yyskmultilearn/problem_transform/__init__.py
yyskmultilearn/problem_transform/br.py
yyskmultilearn/problem_transform/cc.py
yyskmultilearn/problem_transform/lp.py
yy_scikit_multilearn-0.2.2.dist-info/LICENSE
yy_scikit_multilearn-0.2.2.dist-info/METADATA
yy_scikit_multilearn-0.2.2.dist-info/WHEEL
yy_scikit_multilearn-0.2.2.dist-info/top_level.txt
yy_scikit_multilearn-0.2.2.dist-info/RECORD
